llm_dep_extractor/__init__.py
llm_dep_extractor-2025.9.1301013.dist-info/licenses/LICENSE
llm_dep_extractor-2025.9.1301013.dist-info/METADATA
llm_dep_extractor-2025.9.1301013.dist-info/WHEEL
llm_dep_extractor-2025.9.1301013.dist-info/top_level.txt
llm_dep_extractor-2025.9.1301013.dist-info/RECORD
